enr/__init__.py
enr/cli.py
enr/docker.py
enr/nginx.py
enr-0.1.1.dist-info/entry_points.txt
enr-0.1.1.dist-info/licenses/LICENSE
enr-0.1.1.dist-info/WHEEL
enr-0.1.1.dist-info/METADATA
enr-0.1.1.dist-info/RECORD
