Metadata-Version: 2.4
Name: enr
Version: 0.1.1
Summary: CLI utility for easy nginx reverse proxy configuration with automatic redirect handling.
Keywords: nginx,reverse-proxy,docker,cli,devops,proxy,redirect,auto-redirect
Author-email: Pavel Serikov <devpasha@proton.me>
Requires-Python: >=3.10
License-Expression: MIT
Classifier: Development Status :: 4 - Beta
Classifier: Intended Audience :: Developers
Classifier: Intended Audience :: System Administrators
Classifier: Operating System :: OS Independent
Classifier: Programming Language :: Python :: 3
Classifier: Programming Language :: Python :: 3.10
Classifier: Programming Language :: Python :: 3.11
Classifier: Programming Language :: Python :: 3.12
Classifier: Topic :: Internet :: WWW/HTTP :: HTTP Servers
Classifier: Topic :: System :: Systems Administration
Classifier: Topic :: Utilities
License-File: LICENSE
Requires-Dist: pytest>=7.0.0 ; extra == "dev"
Requires-Dist: black>=22.0.0 ; extra == "dev"
Requires-Dist: ruff>=0.1.0 ; extra == "dev"
Requires-Dist: isort>=5.0.0 ; extra == "dev"
Requires-Dist: safety>=2.0.0 ; extra == "dev"
Requires-Dist: bandit>=1.7.0 ; extra == "dev"
Requires-Dist: flit>=3.9.0 ; extra == "dev"
Project-URL: Homepage, https://github.com/pavelsr/enr
Project-URL: Repository, https://github.com/pavelsr/enr
Provides-Extra: dev
